sphinx_modeling/__init__.py
sphinx_modeling/logging.py
sphinx_modeling/modeling/__init__.py
sphinx_modeling/modeling/defaults.py
sphinx_modeling/modeling/main.py
sphinx_modeling/modeling/work_in_progress/all_in_one.py
sphinx_modeling/modeling/work_in_progress/typing_analysis.ods
sphinx_modeling/setup.py
sphinx_modeling-0.2.0.dist-info/METADATA
sphinx_modeling-0.2.0.dist-info/WHEEL
sphinx_modeling-0.2.0.dist-info/LICENSE
sphinx_modeling-0.2.0.dist-info/RECORD
