Metadata-Version: 2.1
Name: sphinx-modeling
Version: 0.2.0
Summary: Sphinx extension to enable modeling and set constraints for sphinx-needs
Home-page: http://github.com/useblocks/sphinx-modeling
License: MIT
Author: team useblocks
Author-email: info@useblocks.com
Requires-Python: >=3.7.2,<3.11
Classifier: Development Status :: 4 - Beta
Classifier: Framework :: Sphinx :: Extension
Classifier: Intended Audience :: Developers
Classifier: License :: OSI Approved :: MIT License
Classifier: Operating System :: OS Independent
Classifier: Programming Language :: Python
Classifier: Programming Language :: Python :: 3
Classifier: Programming Language :: Python :: 3.8
Classifier: Programming Language :: Python :: 3.9
Classifier: Programming Language :: Python :: 3.10
Classifier: Programming Language :: Python :: 3
Classifier: Programming Language :: Python :: 3.6
Classifier: Programming Language :: Python :: 3.7
Classifier: Programming Language :: Python :: 3.8
Classifier: Topic :: Documentation
Classifier: Topic :: Utilities
Requires-Dist: docutils (>=0.18.1)
Requires-Dist: pydantic (>=1.9.2,<2.0.0)
Requires-Dist: sphinx (>=5.0)
Requires-Dist: sphinx-needs (>=1.0.1)
Requires-Dist: sphinxcontrib-plantuml (>=0.24,<0.25)
Requires-Dist: typing-extensions (>=4.3.0,<5.0.0) ; python_version >= "3.7" and python_version < "3.8"
Project-URL: Documentation, https://sphinx-modeling.useblocks.com/
Project-URL: Repository, http://github.com/useblocks/sphinx-modeling
